krex/__init__.py
krex/async_support/__init__.py
krex/async_support/ascendex/__init__.py
krex/async_support/ascendex/_account_http.py
krex/async_support/ascendex/_balance_http.py
krex/async_support/ascendex/_http_manager.py
krex/async_support/ascendex/_market_http.py
krex/async_support/ascendex/_trade_http.py
krex/async_support/ascendex/client.py
krex/async_support/ascendex/endpoints/account.py
krex/async_support/ascendex/endpoints/balance.py
krex/async_support/ascendex/endpoints/market.py
krex/async_support/ascendex/endpoints/order.py
krex/async_support/binance/__init__.py
krex/async_support/binance/_account_http.py
krex/async_support/binance/_http_manager.py
krex/async_support/binance/_market_http.py
krex/async_support/binance/_trade_http.py
krex/async_support/binance/client.py
krex/async_support/binance/enums.py
krex/async_support/binance/endpoints/account.py
krex/async_support/binance/endpoints/market.py
krex/async_support/binance/endpoints/trade.py
krex/async_support/bingx/__init__.py
krex/async_support/bingx/_account_http.py
krex/async_support/bingx/_http_manager.py
krex/async_support/bingx/_market_http.py
krex/async_support/bingx/_trade_http.py
krex/async_support/bingx/client.py
krex/async_support/bingx/endpoints/account.py
krex/async_support/bingx/endpoints/market.py
krex/async_support/bingx/endpoints/trade.py
krex/async_support/bitmart/__init__.py
krex/async_support/bitmart/_account_http.py
krex/async_support/bitmart/_http_manager.py
krex/async_support/bitmart/_market_http.py
krex/async_support/bitmart/_trade_http.py
krex/async_support/bitmart/client.py
krex/async_support/bitmart/endpoints/account.py
krex/async_support/bitmart/endpoints/market.py
krex/async_support/bitmart/endpoints/trade.py
krex/async_support/bitmex/__init__.py
krex/async_support/bitmex/_account_http.py
krex/async_support/bitmex/_http_manager.py
krex/async_support/bitmex/_market_http.py
krex/async_support/bitmex/_position_http.py
krex/async_support/bitmex/_trade_http.py
krex-0.20.0.dist-info/licenses/LICENSE
krex-0.20.0.dist-info/METADATA
krex-0.20.0.dist-info/WHEEL
krex-0.20.0.dist-info/top_level.txt
krex-0.20.0.dist-info/RECORD
