Metadata-Version: 2.4
Name: krex
Version: 0.20.0
Summary: A Lightweight Python Package for Low-Latency and Cross-Exchange Trading.
Author-email: Kairos Research <labs@kairosresearch.io>
License: MIT
Project-URL: Repository, https://github.com/kairos-research-ltd/krex
Classifier: Programming Language :: Python :: 3
Classifier: License :: OSI Approved :: MIT License
Classifier: Operating System :: OS Independent
Requires-Python: >=3.11
License-File: LICENSE
Requires-Dist: eth-account>=0.13.7
Requires-Dist: eth-utils>=5.3.0
Requires-Dist: httpx>=0.28.1
Requires-Dist: ipython>=9.3.0
Requires-Dist: msgpack>=1.1.0
Requires-Dist: nest-asyncio>=1.6.0
Requires-Dist: polars>=1.27.1
Requires-Dist: requests>=2.32.3
Dynamic: license-file
